sapcommissions/__init__.py
python_sapcommissions-2.4.6.dist-info/LICENSE
python_sapcommissions-2.4.6.dist-info/METADATA
python_sapcommissions-2.4.6.dist-info/WHEEL
python_sapcommissions-2.4.6.dist-info/top_level.txt
python_sapcommissions-2.4.6.dist-info/RECORD
