Metadata-Version: 2.1
Name: python-sapcommissions
Version: 2.4.6
Summary: sapcommissions is now sapimclient
Author-email: Niels Perfors <niels.perfors1987@gmail.com>
License: MIT
Project-URL: Homepage, https://github.com/niro1987/sapimclient
Project-URL: Repository, https://github.com/niro1987/sapimclient.git
Project-URL: Issues, https://github.com/niro1987/sapimclient/issues
Keywords: SAP,Incentive Management
Classifier: Intended Audience :: Developers
Classifier: License :: OSI Approved :: MIT License
Classifier: Programming Language :: Python :: 3.11
Classifier: Development Status :: 7 - Inactive
Requires-Python: >=3.11
License-File: LICENSE
Requires-Dist: sapimclient
